mcp_csv_database/__init__.py
mcp_csv_database/__main__.py
mcp_csv_database/server.py
mcp_csv_database-0.1.7.dist-info/licenses/LICENSE
mcp_csv_database-0.1.7.dist-info/METADATA
mcp_csv_database-0.1.7.dist-info/WHEEL
mcp_csv_database-0.1.7.dist-info/entry_points.txt
mcp_csv_database-0.1.7.dist-info/top_level.txt
mcp_csv_database-0.1.7.dist-info/RECORD
