Metadata-Version: 2.4
Name: mcp-csv-database
Version: 0.1.7
Summary: MCP server for CSV file management and SQL querying
Author-email: Lasitha <lasitha.work@gmail.com>
Maintainer-email: Lasitha <lasitha.work@gmail.com>
License-Expression: MIT
Project-URL: Homepage, https://github.com/Lasitha-Jayawardana/mcp-csv-database
Project-URL: Documentation, https://github.com/Lasitha-Jayawardana/mcp-csv-database#readme
Project-URL: Repository, https://github.com/Lasitha-Jayawardana/mcp-csv-database.git
Project-URL: Issues, https://github.com/Lasitha-Jayawardana/mcp-csv-database/issues
Project-URL: Changelog, https://github.com/Lasitha-Jayawardana/mcp-csv-database/blob/main/CHANGELOG.md
Keywords: mcp,csv,database,sql,data-analysis
Classifier: Development Status :: 4 - Beta
Classifier: Intended Audience :: Developers
Classifier: Programming Language :: Python :: 3
Classifier: Programming Language :: Python :: 3.10
Classifier: Programming Language :: Python :: 3.11
Classifier: Programming Language :: Python :: 3.12
Classifier: Topic :: Database
Classifier: Topic :: Scientific/Engineering :: Information Analysis
Classifier: Topic :: Software Development :: Libraries :: Python Modules
Requires-Python: >=3.10
License-File: LICENSE
Requires-Dist: mcp>=1.0.0
Requires-Dist: pandas>=1.3.0
Provides-Extra: dev
Requires-Dist: pytest>=7.0.0; extra == "dev"
Requires-Dist: pytest-cov>=4.0.0; extra == "dev"
Requires-Dist: black>=22.0.0; extra == "dev"
Requires-Dist: isort>=5.0.0; extra == "dev"
Requires-Dist: flake8>=5.0.0; extra == "dev"
Requires-Dist: mypy>=1.0.0; extra == "dev"
Requires-Dist: pandas-stubs>=2.0.0; extra == "dev"
Dynamic: license-file
